{"page_info": {"created_at": "1565857188", "created_by_id": "5295260", "name": "clef101", "rating_vote": "6", "rating": "6", "tags": ["clef\u535a\u58eb", "en", "\u6545\u4e8b", "\u7ffb\u8b6f", "\u8aaa\u660e"], "status": "ONLINE"}, "votes": [{"id": "5344757", "name": "Bales20147", "vote": "UV"}, {"id": "4990678", "name": "Dr V Valentine", "vote": "UV"}, {"id": "4357011", "name": "feitag", "vote": "UV"}, {"id": "6258289", "name": "KarlKaku", "vote": "UV"}, {"id": "5653267", "name": "Nihilmace", "vote": "UV"}, {"id": "5013754", "name": "ting129", "vote": "UV"}], "rating": 6, "votes_jstf": [{"id": "5344757", "name": "Bales20147", "vote": "UV"}, {"id": "4990678", "name": "Dr V Valentine", "vote": "UV"}, {"id": "4357011", "name": "feitag", "vote": "UV"}, {"id": "6258289", "name": "KarlKaku", "vote": "UV"}, {"id": "5653267", "name": "Nihilmace", "vote": "UV"}, {"id": "5013754", "name": "ting129", "vote": "UV"}], "rating_jstf": 6, "votes_removed": [], "rating_removed": 0, "viability": true}