{"page_info": {"created_at": "1585123875", "created_by_id": "5604919", "name": "the-thing-at-the-bottom-of-my-dreams", "rating_vote": "4", "rating": "4", "tags": ["en", "en-\u672b\u65e52018", "\u6545\u4e8b", "\u6b32\u8089\u6559", "\u6d41\u6d6a\u8005\u5716\u66f8\u9928", "\u7329\u7d05\u4e4b\u738b", "\u7b2c\u4e94\u6559\u6703", "\u7ffb\u8b6f"], "status": "ONLINE"}, "votes": [{"id": "5344757", "name": "Bales20147", "vote": "UV"}, {"id": "4990678", "name": "Dr V Valentine", "vote": "UV"}, {"id": "7513990", "name": "KaiTenno", "vote": "UV"}, {"id": "5334590", "name": "Lostwhat", "vote": "UV"}], "rating": 4, "votes_jstf": [{"id": "5344757", "name": "Bales20147", "vote": "UV"}, {"id": "4990678", "name": "Dr V Valentine", "vote": "UV"}, {"id": "7513990", "name": "KaiTenno", "vote": "UV"}, {"id": "5334590", "name": "Lostwhat", "vote": "UV"}], "rating_jstf": 4, "votes_removed": [], "rating_removed": 0, "viability": true}