{"page_info": {"created_at": "1589715032", "created_by_id": "5206218", "name": "just-fuck-it-up-irl", "rating_vote": "7", "rating": "7", "tags": ["clef\u535a\u58eb", "en", "kondraki\u535a\u58eb", "\u5353\u6587\u5eb7\u5353\u5947", "\u6545\u4e8b", "\u74f6\u4e2d\u8239", "\u7ffb\u8b6f"], "status": "ONLINE"}, "votes": [{"id": "5344757", "name": "Bales20147", "vote": "UV"}, {"id": "5956873", "name": "Chromeblushowo ", "vote": "UV"}, {"id": "5565302", "name": "Control Z", "vote": "UV"}, {"id": "4990678", "name": "Dr V Valentine", "vote": "UV"}, {"id": "5255954", "name": "Reverberate_a", "vote": "UV"}, {"id": "4442284", "name": "Sigtina", "vote": "UV"}, {"id": "3981670", "name": "Viken-K", "vote": "UV"}], "rating": 7, "votes_jstf": [{"id": "5344757", "name": "Bales20147", "vote": "UV"}, {"id": "5956873", "name": "Chromeblushowo ", "vote": "UV"}, {"id": "5565302", "name": "Control Z", "vote": "UV"}, {"id": "4990678", "name": "Dr V Valentine", "vote": "UV"}, {"id": "5255954", "name": "Reverberate_a", "vote": "UV"}, {"id": "4442284", "name": "Sigtina", "vote": "UV"}, {"id": "3981670", "name": "Viken-K", "vote": "UV"}], "rating_jstf": 7, "votes_removed": [], "rating_removed": 0, "viability": true}