{"page_info": {"created_at": "1591605118", "created_by_id": "5334590", "name": "uiu-orientation", "rating_vote": "9", "rating": "9", "tags": ["en", "uiu", "\u6545\u4e8b", "\u7ffb\u8b6f", "\u8aaa\u660e"], "status": "ONLINE"}, "votes": [{"id": "5344757", "name": "Bales20147", "vote": "UV"}, {"id": "6217438", "name": "Frederica Bernkastel", "vote": "UV"}, {"id": "5684299", "name": "kingdom war", "vote": "UV"}, {"id": "5334590", "name": "Lostwhat", "vote": "UV"}, {"id": "3979351", "name": "minmasterqw", "vote": "UV"}, {"id": "4442284", "name": "Sigtina", "vote": "UV"}, {"id": "5013754", "name": "ting129", "vote": "UV"}, {"id": "4107284", "name": "Unihedron", "vote": "UV"}, {"id": "5454699", "name": "ZH_mercury", "vote": "UV"}], "rating": 9, "votes_jstf": [{"id": "5344757", "name": "Bales20147", "vote": "UV"}, {"id": "6217438", "name": "Frederica Bernkastel", "vote": "UV"}, {"id": "5684299", "name": "kingdom war", "vote": "UV"}, {"id": "5334590", "name": "Lostwhat", "vote": "UV"}, {"id": "3979351", "name": "minmasterqw", "vote": "UV"}, {"id": "4442284", "name": "Sigtina", "vote": "UV"}, {"id": "5013754", "name": "ting129", "vote": "UV"}, {"id": "4107284", "name": "Unihedron", "vote": "UV"}, {"id": "5454699", "name": "ZH_mercury", "vote": "UV"}], "rating_jstf": 9, "votes_removed": [], "rating_removed": 0, "viability": true}