{"page_info": {"created_at": "1594624144", "created_by_id": "3981670", "name": "spc-001", "rating_vote": "6", "rating": "6", "tags": ["en-\u672b\u65e52018", "goi\u683c\u5f0f", "\u6bc6\u6253\u9bca\u9b5a\u4e2d\u5fc3", "\u7ffb\u8b6f", "\u8a6e\u91cb\u8cc7\u6599", "\u9644\u52a0\u8cc7\u6599"], "status": "ONLINE"}, "votes": [{"id": "7975483", "name": "Asaerror", "vote": "UV"}, {"id": "5344757", "name": "Bales20147", "vote": "UV"}, {"id": "4990678", "name": "Dr V Valentine", "vote": "UV"}, {"id": "5684299", "name": "kingdom war", "vote": "UV"}, {"id": "4442284", "name": "Sigtina", "vote": "UV"}, {"id": "6048694", "name": "verdi-ye", "vote": "UV"}], "rating": 6, "votes_jstf": [{"id": "7975483", "name": "Asaerror", "vote": "UV"}, {"id": "5344757", "name": "Bales20147", "vote": "UV"}, {"id": "4990678", "name": "Dr V Valentine", "vote": "UV"}, {"id": "5684299", "name": "kingdom war", "vote": "UV"}, {"id": "4442284", "name": "Sigtina", "vote": "UV"}, {"id": "6048694", "name": "verdi-ye", "vote": "UV"}], "rating_jstf": 6, "votes_removed": [], "rating_removed": 0, "viability": true}